azure/mgmt/serialconsole/__init__.py
azure/mgmt/serialconsole/_configuration.py
azure/mgmt/serialconsole/_microsoft_serial_console_client.py
azure/mgmt/serialconsole/_version.py
azure/mgmt/serialconsole/aio/__init__.py
azure/mgmt/serialconsole/aio/_configuration.py
azure/mgmt/serialconsole/aio/_microsoft_serial_console_client.py
azure/mgmt/serialconsole/aio/operations/__init__.py
azure/mgmt/serialconsole/aio/operations/_microsoft_serial_console_client_operations.py
azure/mgmt/serialconsole/aio/operations/_serial_ports_operations.py
azure/mgmt/serialconsole/models/__init__.py
azure/mgmt/serialconsole/models/_microsoft_serial_console_client_enums.py
azure/mgmt/serialconsole/models/_models.py
azure/mgmt/serialconsole/models/_models_py3.py
azure/mgmt/serialconsole/operations/__init__.py
azure/mgmt/serialconsole/operations/_microsoft_serial_console_client_operations.py
azure/mgmt/serialconsole/operations/_serial_ports_operations.py
azure_mgmt_serialconsole-1.0.0.dist-info/METADATA
azure_mgmt_serialconsole-1.0.0.dist-info/WHEEL
azure_mgmt_serialconsole-1.0.0.dist-info/top_level.txt
azure_mgmt_serialconsole-1.0.0.dist-info/RECORD
